ferromic-0.1.3.dist-info/METADATA
ferromic-0.1.3.dist-info/WHEEL
ferromic-0.1.3.dist-info/licenses/LICENSE.md
ferromic/__init__.py
ferromic/ferromic.pypy311-pp73-ppc_64-linux-gnu.so
ferromic-0.1.3.dist-info/RECORD
