Metadata-Version: 2.4
Name: ferromic
Version: 0.1.3
Classifier: Development Status :: 4 - Beta
Classifier: Intended Audience :: Science/Research
Classifier: License :: Other/Proprietary License
Classifier: Programming Language :: Python
Classifier: Programming Language :: Python :: 3
Classifier: Programming Language :: Rust
Classifier: Topic :: Scientific/Engineering :: Bio-Informatics
Requires-Dist: numpy>=1.23
Requires-Dist: pytest ; extra == 'test'
Requires-Dist: numpy ; extra == 'test'
Requires-Dist: scikit-allel ; extra == 'test'
Requires-Dist: scipy ; extra == 'test'
Requires-Dist: pytest-benchmark ; extra == 'test'
Requires-Dist: patchelf ; platform_system == 'Linux' and extra == 'test'
Provides-Extra: test
License-File: LICENSE.md
Summary: Rust-accelerated population genetics toolkit with ergonomic Python bindings
Keywords: population-genetics,bioinformatics,rust,pyo3,numpy
Home-Page: https://github.com/SauersML/ferromic
Author: SauersML
Requires-Python: >=3.9
